llama_text2sql_eval/__init__.py
llama_text2sql_eval/cli.py
llama_text2sql_eval/llama_text2sql.py
llama_text2sql_eval/main_module.py
llama_text2sql_eval/text2sql_eval.py
llama_text2sql_eval-0.0.4.dist-info/METADATA
llama_text2sql_eval-0.0.4.dist-info/WHEEL
llama_text2sql_eval-0.0.4.dist-info/entry_points.txt
llama_text2sql_eval-0.0.4.dist-info/top_level.txt
llama_text2sql_eval-0.0.4.dist-info/RECORD
