Metadata-Version: 2.4
Name: llama-text2sql-eval
Version: 0.0.4
Summary: A Quick Llama Text2SQL Evaluation Library
Author: Jeff Tang
License: MIT
Project-URL: Homepage, https://github.com/meta-llama/llama-cookbook/tree/text2sql/end-to-end-use-cases/coding/text2sql/eval
Keywords: llama,text2sql,eval
Classifier: Programming Language :: Python :: 3
Classifier: License :: OSI Approved :: MIT License
Classifier: Operating System :: OS Independent
Requires-Python: >=3.10
Requires-Dist: datasets==3.6.0
Requires-Dist: llama_api_client==0.1.2
Requires-Dist: func_timeout==4.3.5
